README.txt
setup.cfg
setup.py
Products/__init__.py
Products.RFC822AddressFieldValidator.egg-info/PKG-INFO
Products.RFC822AddressFieldValidator.egg-info/SOURCES.txt
Products.RFC822AddressFieldValidator.egg-info/SOURCES.txt~
Products.RFC822AddressFieldValidator.egg-info/dependency_links.txt
Products.RFC822AddressFieldValidator.egg-info/entry_points.txt
Products.RFC822AddressFieldValidator.egg-info/namespace_packages.txt
Products.RFC822AddressFieldValidator.egg-info/not-zip-safe
Products.RFC822AddressFieldValidator.egg-info/requires.txt
Products.RFC822AddressFieldValidator.egg-info/top_level.txt
Products/RFC822AddressFieldValidator/__init__.py
Products/RFC822AddressFieldValidator/changes.txt
Products/RFC822AddressFieldValidator/readme.txt
Products/RFC822AddressFieldValidator/validator.py