Metadata-Version: 1.0
Name: Products.RFC822AddressFieldValidator
Version: 1.0b
Summary: Validator for complex (multiple address) RFC822 header fields
Home-page: http://www.nidelven-it.no/d
Author: Nidelven IT
Author-email: info@nidelven-it.no
License: GPL
Keywords: python plone archetypes validation email
Platform: UNKNOWN
Classifier: Programming Language :: Python
Classifier: Framework :: Zope2
Classifier: Framework :: Plone
